{
  "artifacts": [],
  "command": "fit_bnn",
  "experiment": {
    "base_dir": "/home/freidanm/repos/pytorch_experiments/pysgmcmc_experiments",
    "dependencies": [
      "numpy==1.14.3",
      "pysgmcmc==0.0.1",
      "sacred==0.7.3"
    ],
    "mainfile": "bnn_sinc.py",
    "name": "BNN_SINC",
    "repositories": [],
    "sources": [
      [
        "bnn_sinc.py",
        "_sources/bnn_sinc_d006a01b29cb249ce29827b15d182abf.py"
      ],
      [
        "utils.py",
        "_sources/utils_3bdfe4d17068fc05d51c766034aa01f0.py"
      ]
    ]
  },
  "heartbeat": "2018-06-06T06:41:05.903016",
  "host": {
    "ENV": {},
    "cpu": "Intel(R) Xeon(R) CPU E5-2650 v2 @ 2.60GHz",
    "hostname": "metaex05",
    "os": [
      "Linux",
      "Linux-4.4.0-112-generic-x86_64-with-Ubuntu-16.04-xenial"
    ],
    "python_version": "3.5.2"
  },
  "meta": {
    "command": "fit_bnn",
    "options": {
      "--beat_interval": null,
      "--capture": null,
      "--comment": null,
      "--debug": false,
      "--enforce_clean": false,
      "--file_storage": null,
      "--force": false,
      "--help": false,
      "--loglevel": null,
      "--mongo_db": null,
      "--name": null,
      "--pdb": false,
      "--print_config": false,
      "--priority": null,
      "--queue": false,
      "--sql": null,
      "--tiny_db": null,
      "--unobserved": false
    }
  },
  "resources": [],
  "result": {
    "packages": [
      [
        "atomicwrites",
        "1.1.5"
      ],
      [
        "attrs",
        "18.1.0"
      ],
      [
        "backcall",
        "0.1.0"
      ],
      [
        "coverage",
        "4.5.1"
      ],
      [
        "cycler",
        "0.10.0"
      ],
      [
        "decorator",
        "4.3.0"
      ],
      [
        "docopt",
        "0.6.2"
      ],
      [
        "hashfs",
        "0.7.0"
      ],
      [
        "hypothesis",
        "3.57.0"
      ],
      [
        "ipykernel",
        "4.8.2"
      ],
      [
        "ipython",
        "6.4.0"
      ],
      [
        "ipython-genutils",
        "0.2.0"
      ],
      [
        "jedi",
        "0.12.0"
      ],
      [
        "jsonpickle",
        "0.9.6"
      ],
      [
        "jsonschema",
        "2.6.0"
      ],
      [
        "jupyter-client",
        "5.2.3"
      ],
      [
        "jupyter-core",
        "4.4.0"
      ],
      [
        "kiwisolver",
        "1.0.1"
      ],
      [
        "Lasagne",
        "0.1"
      ],
      [
        "matplotlib",
        "2.2.2"
      ],
      [
        "more-itertools",
        "4.2.0"
      ],
      [
        "mpmath",
        "1.0.0"
      ],
      [
        "munch",
        "2.3.2"
      ],
      [
        "nbformat",
        "4.4.0"
      ],
      [
        "nbval",
        "0.9.1"
      ],
      [
        "numpy",
        "1.14.3"
      ],
      [
        "pandas",
        "0.23.0"
      ],
      [
        "parso",
        "0.2.1"
      ],
      [
        "pexpect",
        "4.6.0"
      ],
      [
        "pickleshare",
        "0.7.4"
      ],
      [
        "Pillow",
        "5.1.0"
      ],
      [
        "pip",
        "10.0.1"
      ],
      [
        "pkg-resources",
        "0.0.0"
      ],
      [
        "pluggy",
        "0.6.0"
      ],
      [
        "prompt-toolkit",
        "1.0.15"
      ],
      [
        "ptyprocess",
        "0.5.2"
      ],
      [
        "py",
        "1.5.3"
      ],
      [
        "py-cpuinfo",
        "4.0.0"
      ],
      [
        "Pygments",
        "2.2.0"
      ],
      [
        "pymongo",
        "3.6.1"
      ],
      [
        "pyparsing",
        "2.2.0"
      ],
      [
        "pysgmcmc",
        "0.0.1"
      ],
      [
        "pytest",
        "3.6.0"
      ],
      [
        "python-dateutil",
        "2.7.3"
      ],
      [
        "pytz",
        "2018.4"
      ],
      [
        "pyzmq",
        "17.0.0"
      ],
      [
        "sacred",
        "0.7.3"
      ],
      [
        "scandir",
        "1.7"
      ],
      [
        "scikit-learn",
        "0.19.1"
      ],
      [
        "scipy",
        "1.1.0"
      ],
      [
        "seaborn",
        "0.8.1"
      ],
      [
        "setuptools",
        "39.2.0"
      ],
      [
        "simplegeneric",
        "0.8.1"
      ],
      [
        "six",
        "1.11.0"
      ],
      [
        "SQLAlchemy",
        "1.2.8"
      ],
      [
        "sympy",
        "1.1.1"
      ],
      [
        "Theano",
        "0.8.0"
      ],
      [
        "tinydb",
        "3.9.0.post1"
      ],
      [
        "tinydb-serialization",
        "1.0.4"
      ],
      [
        "torch",
        "0.4.0"
      ],
      [
        "torchvision",
        "0.2.1"
      ],
      [
        "tornado",
        "5.0.2"
      ],
      [
        "tqdm",
        "4.23.4"
      ],
      [
        "traitlets",
        "4.3.2"
      ],
      [
        "wcwidth",
        "0.1.7"
      ],
      [
        "wheel",
        "0.31.1"
      ],
      [
        "wrapt",
        "1.10.11"
      ]
    ],
    "prediction_mean": [
      0.0385647714138031,
      0.039290402084589005,
      0.04026450961828232,
      0.03838220611214638,
      0.037726275622844696,
      0.03690735995769501,
      0.034962330013513565,
      0.03228851035237312,
      0.028947841376066208,
      0.02731313928961754,
      0.025268658995628357,
      0.023421017453074455,
      0.022877691313624382,
      0.022619124501943588,
      0.022506102919578552,
      0.02247304655611515,
      0.022531576454639435,
      0.022727005183696747,
      0.023311924189329147,
      0.02564028650522232,
      0.03116295486688614,
      0.038308579474687576,
      0.04128498584032059,
      0.04234734922647476,
      0.04275261238217354,
      0.04299427941441536,
      0.04307234287261963,
      0.04162968695163727,
      0.04052809253334999,
      0.03747114539146423,
      0.02851536124944687,
      0.024646572768688202,
      0.03804291784763336,
      0.15430848300457,
      0.30095213651657104,
      0.3822634816169739,
      0.4088561534881592,
      0.435580313205719,
      0.4664332866668701,
      0.4914126992225647,
      0.5210923552513123,
      0.5798475742340088,
      0.6083683967590332,
      0.6590234637260437,
      0.6796086430549622,
      0.7198562622070312,
      0.7143984436988831,
      0.6691381335258484,
      0.6141465306282043,
      0.542924165725708,
      0.3868732452392578,
      0.16341206431388855,
      -0.011052515357732773,
      -0.0645446926355362,
      -0.054584793746471405,
      -0.06267370283603668,
      -0.0744800791144371,
      -0.06182475388050079,
      -0.0651029720902443,
      -0.06354261189699173,
      -0.07819691300392151,
      -0.0954628735780716,
      -0.09370444715023041,
      -0.09308746457099915,
      -0.09112529456615448,
      -0.09002959728240967,
      -0.0805148258805275,
      -0.07777078449726105,
      -0.07494191825389862,
      -0.06828282028436661,
      -0.06519240140914917,
      -0.05210484564304352,
      -0.04035751521587372,
      -0.032261528074741364,
      -0.027497485280036926,
      -0.027443580329418182,
      -0.028336241841316223,
      -0.03052377700805664,
      -0.03261566907167435,
      -0.03296300023794174,
      -0.03315652161836624,
      -0.032937489449977875,
      -0.030663803219795227,
      -0.02438737452030182,
      -0.014367736876010895,
      -0.006864514201879501,
      -0.0027198195457458496,
      -0.000510580837726593,
      0.0028285011649131775,
      0.003843456506729126,
      0.007300466299057007,
      0.007564634084701538,
      0.006174493581056595,
      0.006477314978837967,
      0.006530039012432098,
      0.006490536034107208,
      0.007326114922761917,
      0.008358102291822433,
      0.009748782962560654,
      0.009685434401035309
    ],
    "prediction_std": [
      0.023518012836575508,
      0.023192932829260826,
      0.028293387964367867,
      0.020669762045145035,
      0.0191468745470047,
      0.017214953899383545,
      0.01944999024271965,
      0.02187119610607624,
      0.02283664420247078,
      0.024413051083683968,
      0.024990735575556755,
      0.02641395665705204,
      0.02766134776175022,
      0.028362471610307693,
      0.028695501387119293,
      0.028824839740991592,
      0.02880278043448925,
      0.028544243425130844,
      0.02741786651313305,
      0.024205496534705162,
      0.017092352733016014,
      0.012343542650341988,
      0.015383659861981869,
      0.01638156734406948,
      0.017051536589860916,
      0.017201416194438934,
      0.017158806324005127,
      0.018906015902757645,
      0.018400192260742188,
      0.018349681049585342,
      0.023521052673459053,
      0.03766116499900818,
      0.05535978078842163,
      0.2599791884422302,
      0.33463209867477417,
      0.37011969089508057,
      0.37956875562667847,
      0.3745368421077728,
      0.3771180808544159,
      0.37115269899368286,
      0.36290159821510315,
      0.3178551197052002,
      0.3059336245059967,
      0.2650658190250397,
      0.23958224058151245,
      0.09868187457323074,
      0.11816299706697464,
      0.2044232338666916,
      0.3168744742870331,
      0.35967570543289185,
      0.4054562747478485,
      0.39045119285583496,
      0.3965071439743042,
      0.3215250074863434,
      0.3049265146255493,
      0.32133638858795166,
      0.2740207016468048,
      0.2165350764989853,
      0.16348068416118622,
      0.13143399357795715,
      0.10150103271007538,
      0.08102021366357803,
      0.07540176063776016,
      0.07554326206445694,
      0.07529058307409286,
      0.07412076741456985,
      0.07188085466623306,
      0.06927849352359772,
      0.06844624876976013,
      0.06919518858194351,
      0.07027976959943771,
      0.07172991335391998,
      0.07320497184991837,
      0.07615850865840912,
      0.07539362460374832,
      0.07532371580600739,
      0.07373405247926712,
      0.07110709697008133,
      0.06864067912101746,
      0.06944374740123749,
      0.07008467614650726,
      0.06968755275011063,
      0.06907012313604355,
      0.06939532607793808,
      0.06761103123426437,
      0.06805143505334854,
      0.07549817860126495,
      0.07628811150789261,
      0.0747508630156517,
      0.07437403500080109,
      0.07327708601951599,
      0.07331898808479309,
      0.07540851086378098,
      0.07514366507530212,
      0.07420499622821808,
      0.07413756847381592,
      0.07390422374010086,
      0.07321339100599289,
      0.07296101748943329,
      0.0730980858206749
    ],
    "x_test": [
      [
        0.0
      ],
      [
        0.010101010101010102
      ],
      [
        0.020202020202020204
      ],
      [
        0.030303030303030304
      ],
      [
        0.04040404040404041
      ],
      [
        0.05050505050505051
      ],
      [
        0.06060606060606061
      ],
      [
        0.07070707070707072
      ],
      [
        0.08080808080808081
      ],
      [
        0.09090909090909091
      ],
      [
        0.10101010101010102
      ],
      [
        0.11111111111111112
      ],
      [
        0.12121212121212122
      ],
      [
        0.13131313131313133
      ],
      [
        0.14141414141414144
      ],
      [
        0.15151515151515152
      ],
      [
        0.16161616161616163
      ],
      [
        0.17171717171717174
      ],
      [
        0.18181818181818182
      ],
      [
        0.19191919191919193
      ],
      [
        0.20202020202020204
      ],
      [
        0.21212121212121213
      ],
      [
        0.22222222222222224
      ],
      [
        0.23232323232323235
      ],
      [
        0.24242424242424243
      ],
      [
        0.25252525252525254
      ],
      [
        0.26262626262626265
      ],
      [
        0.27272727272727276
      ],
      [
        0.2828282828282829
      ],
      [
        0.29292929292929293
      ],
      [
        0.30303030303030304
      ],
      [
        0.31313131313131315
      ],
      [
        0.32323232323232326
      ],
      [
        0.33333333333333337
      ],
      [
        0.3434343434343435
      ],
      [
        0.3535353535353536
      ],
      [
        0.36363636363636365
      ],
      [
        0.37373737373737376
      ],
      [
        0.38383838383838387
      ],
      [
        0.393939393939394
      ],
      [
        0.4040404040404041
      ],
      [
        0.4141414141414142
      ],
      [
        0.42424242424242425
      ],
      [
        0.43434343434343436
      ],
      [
        0.4444444444444445
      ],
      [
        0.4545454545454546
      ],
      [
        0.4646464646464647
      ],
      [
        0.4747474747474748
      ],
      [
        0.48484848484848486
      ],
      [
        0.494949494949495
      ],
      [
        0.5050505050505051
      ],
      [
        0.5151515151515152
      ],
      [
        0.5252525252525253
      ],
      [
        0.5353535353535354
      ],
      [
        0.5454545454545455
      ],
      [
        0.5555555555555556
      ],
      [
        0.5656565656565657
      ],
      [
        0.5757575757575758
      ],
      [
        0.5858585858585859
      ],
      [
        0.595959595959596
      ],
      [
        0.6060606060606061
      ],
      [
        0.6161616161616162
      ],
      [
        0.6262626262626263
      ],
      [
        0.6363636363636365
      ],
      [
        0.6464646464646465
      ],
      [
        0.6565656565656566
      ],
      [
        0.6666666666666667
      ],
      [
        0.6767676767676768
      ],
      [
        0.686868686868687
      ],
      [
        0.696969696969697
      ],
      [
        0.7070707070707072
      ],
      [
        0.7171717171717172
      ],
      [
        0.7272727272727273
      ],
      [
        0.7373737373737375
      ],
      [
        0.7474747474747475
      ],
      [
        0.7575757575757577
      ],
      [
        0.7676767676767677
      ],
      [
        0.7777777777777778
      ],
      [
        0.787878787878788
      ],
      [
        0.797979797979798
      ],
      [
        0.8080808080808082
      ],
      [
        0.8181818181818182
      ],
      [
        0.8282828282828284
      ],
      [
        0.8383838383838385
      ],
      [
        0.8484848484848485
      ],
      [
        0.8585858585858587
      ],
      [
        0.8686868686868687
      ],
      [
        0.8787878787878789
      ],
      [
        0.888888888888889
      ],
      [
        0.8989898989898991
      ],
      [
        0.9090909090909092
      ],
      [
        0.9191919191919192
      ],
      [
        0.9292929292929294
      ],
      [
        0.9393939393939394
      ],
      [
        0.9494949494949496
      ],
      [
        0.9595959595959597
      ],
      [
        0.9696969696969697
      ],
      [
        0.9797979797979799
      ],
      [
        0.98989898989899
      ],
      [
        1.0
      ]
    ],
    "x_train": [
      [
        0.45805494822409054
      ],
      [
        0.30834960696491165
      ],
      [
        0.23148704503556228
      ],
      [
        0.2774245517561259
      ],
      [
        0.8172348119026699
      ],
      [
        0.11134663609249817
      ],
      [
        0.6264372289542525
      ],
      [
        0.2767878866365143
      ],
      [
        0.6821746741884953
      ],
      [
        0.678970783910743
      ],
      [
        0.7967174185877428
      ],
      [
        0.04580216252273306
      ],
      [
        0.9125982744103684
      ],
      [
        0.21381598633706667
      ],
      [
        0.3036373012725162
      ],
      [
        0.9890636234503387
      ],
      [
        0.18588150292112893
      ],
      [
        0.9887248354111614
      ],
      [
        0.7500842313719652
      ],
      [
        0.222386045114342
      ]
    ],
    "y_test": [
      3.898171832519376e-17,
      0.020274246861848165,
      0.03933498333909508,
      0.055203161892331855,
      0.0661352253962204,
      0.07080609473712546,
      0.06845863724555595,
      0.05900373465409052,
      0.043059217618867184,
      0.02192135198060222,
      -0.002531220696610386,
      -0.027994729601457623,
      -0.05194625476850527,
      -0.07188083931840027,
      -0.08555844589083125,
      -0.09123763929204888,
      -0.08787313853403564,
      -0.0752567820872474,
      -0.054085842507903686,
      -0.02594867486647478,
      0.006775110522284362,
      0.04109501600716735,
      0.07365803431668248,
      0.10104575277198334,
      0.12009563035612007,
      0.12821862978460435,
      0.12368448743565288,
      0.10584752683830692,
      0.07529000284951066,
      0.0338662197122978,
      -0.01536138745742742,
      -0.06829402787132798,
      -0.12006672743918213,
      -0.16539866862653782,
      -0.1989979808377625,
      -0.21598973960183296,
      -0.21233289506764946,
      -0.18519162011407383,
      -0.13322923082935628,
      -0.056798225363788,
      0.04199228757252567,
      0.15934104688703798,
      0.28994984251555567,
      0.4273377947651787,
      0.5642532787936153,
      0.6931538911162701,
      0.8067189701511421,
      0.8983560982788098,
      0.9626630110511456,
      0.9958094461093097,
      0.9958094461093094,
      0.962663011051145,
      0.8983560982788091,
      0.8067189701511414,
      0.693153891116269,
      0.5642532787936153,
      0.4273377947651775,
      0.28994984251555567,
      0.15934104688703798,
      0.04199228757252475,
      -0.05679822536378837,
      -0.1332292308293572,
      -0.18519162011407397,
      -0.2123328950676497,
      -0.21598973960183288,
      -0.19899798083776235,
      -0.16539866862653715,
      -0.12006672743918172,
      -0.06829402787132753,
      -0.015361387457426982,
      0.03386621971229819,
      0.07529000284951098,
      0.10584752683830712,
      0.12368448743565298,
      0.12821862978460433,
      0.1200956303561199,
      0.10104575277198308,
      0.07365803431668248,
      0.04109501600716697,
      0.006775110522284362,
      -0.025948674866474952,
      -0.054085842507903686,
      -0.07525678208724748,
      -0.0878731385340357,
      -0.09123763929204888,
      -0.08555844589083114,
      -0.07188083931840027,
      -0.05194625476850502,
      -0.027994729601457623,
      -0.0025312206966099596,
      0.021921351980602476,
      0.043059217618867184,
      0.05900373465409081,
      0.06845863724555602,
      0.07080609473712543,
      0.06613522539622031,
      0.055203161892331855,
      0.03933498333909478,
      0.020274246861847946,
      3.898171832519376e-17
    ],
    "y_train": [
      0.734705222071769,
      -0.043068965274884886,
      0.09905466138898567,
      0.09313644774296755,
      -0.051712361521517515,
      -0.028580378737965834,
      -0.18587007727771,
      0.09501657492217765,
      -0.09281289141506874,
      -0.1091380058823602,
      0.011043390157538054,
      0.06947322016160516,
      0.02974304125387095,
      0.04677497367301745,
      -0.018483096928064588,
      0.021924507957984094,
      -0.043487095201782476,
      0.022591145483834292,
      0.12728062460001402,
      0.07415257341662396
    ]
  },
  "start_time": "2018-06-06T06:39:57.401465",
  "status": "COMPLETED",
  "stop_time": "2018-06-06T06:41:05.901175"
}